voice_notes/__init__.py
voice_notes/app.py
voice_notes/core/__init__.py
voice_notes/core/audio_devices.py
voice_notes/core/audio_library.py
voice_notes/core/config.py
voice_notes/core/notes_manager.py
voice_notes/core/recorder.py
voice_notes/core/transcribe.py
voice_notes/core/transcription.py
voice_notes/core/translation.py
voice_notes/styles/__init__.py
voice_notes/styles/theme.py
voice_notes/ui/__init__.py
voice_notes/ui/main_window.py
voice_notes/utils/__init__.py
voice_notes/utils/helpers.py
voice_notes/utils/platform.py
voice_notes/widgets/__init__.py
voice_notes/widgets/library_widget.py
voice_notes/widgets/media_widget.py
voice_notes/widgets/notes_widget.py
voice_notes/widgets/player_widget.py
voice_notes/widgets/recorder_widget.py
voice_notes/widgets/transcription_widget.py
voice_notes-0.1.0.dist-info/licenses/LICENSE
voice_notes-0.1.0.dist-info/METADATA
voice_notes-0.1.0.dist-info/WHEEL
voice_notes-0.1.0.dist-info/entry_points.txt
voice_notes-0.1.0.dist-info/top_level.txt
voice_notes-0.1.0.dist-info/RECORD
