Metadata-Version: 2.4
Name: voice-notes
Version: 0.1.0
Summary: A voice recording and transcription application
License-Expression: MIT
Project-URL: Homepage, https://github.com/zangjiucheng/Voice-Notes
Project-URL: Repository, https://github.com/zangjiucheng/Voice-Notes
Classifier: Development Status :: 3 - Alpha
Classifier: Intended Audience :: End Users/Desktop
Classifier: Operating System :: OS Independent
Classifier: Programming Language :: Python :: 3
Classifier: Programming Language :: Python :: 3.9
Classifier: Programming Language :: Python :: 3.10
Classifier: Programming Language :: Python :: 3.11
Classifier: Programming Language :: Python :: 3.12
Classifier: Programming Language :: Python :: 3.13
Classifier: Topic :: Multimedia :: Sound/Audio :: Analysis
Requires-Python: >=3.9
License-File: LICENSE
Requires-Dist: faster-whisper
Requires-Dist: PyQt6
Requires-Dist: PyQt6-Qt6
Requires-Dist: PyQt6-sip
Requires-Dist: numpy
Requires-Dist: pydub
Requires-Dist: soundfile
Requires-Dist: sounddevice
Requires-Dist: deep-translator
Dynamic: license-file
